refgenieserver/__init__.py
refgenieserver/__main__.py
refgenieserver/_version.py
refgenieserver/const.py
refgenieserver/data_models.py
refgenieserver/helpers.py
refgenieserver/main.py
refgenieserver/server_builder.py
refgenieserver/routers/private.py
refgenieserver/routers/version1.py
refgenieserver/routers/version2.py
refgenieserver/routers/version3.py
refgenieserver/static/refgenie.ico
refgenieserver/static/refgenie_bug.svg
refgenieserver/static/refgenie_logo.svg
refgenieserver/static/style.css
refgenieserver/templates/asset.html
refgenieserver/templates/base.html
refgenieserver/templates/footer.html
refgenieserver/templates/index.html
refgenieserver/templates/navbar.html
refgenieserver/templates/v3/asset.html
refgenieserver/templates/v3/base.html
refgenieserver/templates/v3/footer.html
refgenieserver/templates/v3/genome.html
refgenieserver/templates/v3/index.html
refgenieserver/templates/v3/navbar.html
refgenieserver-0.7.0.dist-info/LICENSE.txt
refgenieserver-0.7.0.dist-info/METADATA
refgenieserver-0.7.0.dist-info/WHEEL
refgenieserver-0.7.0.dist-info/entry_points.txt
refgenieserver-0.7.0.dist-info/top_level.txt
refgenieserver-0.7.0.dist-info/RECORD
