Metadata-Version: 2.1
Name: refgenieserver
Version: 0.7.0
Summary: This server provides both a web interface and a RESTful API. Users may explore and download archived indexes from the web interface or develop tools that programmatically query the API.
Home-page: https://refgenie.databio.org/
Author: Michal Stolarczyk, Vince Reuter, Nathan Sheffield
License: BSD2
Keywords: project,bioinformatics,sequencing,ngs,workflow,GUI,genomes,server
Platform: UNKNOWN
Classifier: Development Status :: 4 - Beta
Classifier: License :: OSI Approved :: BSD License
Classifier: Programming Language :: Python :: 3.5
Classifier: Programming Language :: Python :: 3.6
Classifier: Programming Language :: Python :: 3.7
Classifier: Programming Language :: Python :: 3.8
Classifier: Topic :: Scientific/Engineering :: Bio-Informatics
Requires-Dist: aiofiles
Requires-Dist: fastapi
Requires-Dist: jinja2
Requires-Dist: logmuse (>=0.2)
Requires-Dist: refgenconf (>=0.11.0)
Requires-Dist: ubiquerg (>=0.6.1)
Requires-Dist: uvicorn (>=0.7.1)
